histolab/__init__.py
histolab/data/__init__.py
histolab/data/_registry.py
histolab/data/cmu_small_region.svs
histolab/exceptions.py
histolab/filters/__init__.py
histolab/filters/compositions.py
histolab/filters/image_filters.py
histolab/filters/image_filters_functional.py
histolab/filters/morphological_filters.py
histolab/filters/morphological_filters_functional.py
histolab/filters/util.py
histolab/masks.py
histolab/mixins.py
histolab/scorer.py
histolab/slide.py
histolab/stain_normalizer.py
histolab/tile.py
histolab/tiler.py
histolab/types.py
histolab/util.py
histolab-0.7.0.dist-info/LICENSE.txt
histolab-0.7.0.dist-info/METADATA
histolab-0.7.0.dist-info/WHEEL
histolab-0.7.0.dist-info/RECORD
