Metadata-Version: 2.1
Name: histolab
Version: 0.7.0
Summary: Python library for Digital Pathology Image Processing
Home-page: https://github.com/histolab/histolab
License: Apache-2.0
Author: E. Arbitrio, N. Bussola, A. Marcolini
Maintainer: Ernesto Arbitrio
Maintainer-email: ernesto.arbitrio@gmail.com
Requires-Python: >=3.8,<3.12
Classifier: Intended Audience :: Science/Research
Classifier: License :: OSI Approved :: Apache Software License
Classifier: Operating System :: OS Independent
Classifier: Programming Language :: Python :: 3
Classifier: Programming Language :: Python :: 3.8
Classifier: Programming Language :: Python :: 3.9
Classifier: Programming Language :: Python :: 3.10
Classifier: Programming Language :: Python :: 3.11
Provides-Extra: docs
Requires-Dist: Pillow (>=9.1.0,<11.0.0)
Requires-Dist: Sphinx (>=5.1.1,<8.0.0) ; extra == "docs"
Requires-Dist: certifi (>=2023.7.22)
Requires-Dist: numpy (>=1.23.2,<=1.24.4)
Requires-Dist: openslide-python (>=1.3.1,<1.3.2)
Requires-Dist: scikit-image (>=0.19.0,<0.19.4)
Requires-Dist: scipy (>=1.5.0,<1.10.1)
Requires-Dist: sphinx-prompt (==1.7.0) ; (python_version >= "3.8" and python_version < "3.9") and (extra == "docs")
Requires-Dist: sphinx-prompt (==1.8.0) ; (python_version >= "3.9" and python_version < "4.0") and (extra == "docs")
Requires-Dist: sphinx-rtd-theme (>=1,<3) ; extra == "docs"
Requires-Dist: sphinxcontrib-katex (>=0.8.6,<0.10.0) ; extra == "docs"
Requires-Dist: sphinxemoji (>=0.2.0,<0.3.0) ; extra == "docs"
Project-URL: Documentation, https://histolab.readthedocs.io
Project-URL: Repository, https://github.com/histolab/histolab
